src/__init__.py
src/cli.py
src/compression_manager.py
src/config_manager.py
src/inventory_parser.py
src/journal_collector.py
src/log_collector.py
src/probe_manager.py
src/raw_mode_manager.py
src/rsync_manager.py
flp_log_gatherer-1.1.0.dist-info/METADATA
flp_log_gatherer-1.1.0.dist-info/WHEEL
flp_log_gatherer-1.1.0.dist-info/entry_points.txt
flp_log_gatherer-1.1.0.dist-info/top_level.txt
flp_log_gatherer-1.1.0.dist-info/RECORD
