Metadata-Version: 2.4
Name: flp-log-gatherer
Version: 1.1.0
Summary: Collect logs from heterogeneous nodes using rsync and systemd journal
Home-page: https://github.com/mconcas/flp-log-gatherer
Author: Matteo Concas
Author-email: Matteo Concas <matteo.concas@cern.ch>
License-Expression: MIT
Project-URL: Homepage, https://github.com/mconcas/flp-log-gatherer
Project-URL: Repository, https://github.com/mconcas/flp-log-gatherer
Keywords: logs,rsync,systemd,journal,collection,monitoring
Classifier: Development Status :: 4 - Beta
Classifier: Intended Audience :: System Administrators
Classifier: Programming Language :: Python :: 3
Classifier: Programming Language :: Python :: 3.7
Classifier: Programming Language :: Python :: 3.8
Classifier: Programming Language :: Python :: 3.9
Classifier: Programming Language :: Python :: 3.10
Classifier: Programming Language :: Python :: 3.11
Classifier: Topic :: System :: Logging
Classifier: Topic :: System :: Monitoring
Requires-Python: >=3.7
Requires-Dist: PyYAML>=5.1
Dynamic: author
Dynamic: home-page
Dynamic: requires-python
